bertopic_easy/__init__.py
bertopic_easy/chain.py
bertopic_easy/classify_outliers.py
bertopic_easy/cluster.py
bertopic_easy/embedding.py
bertopic_easy/input_examples.py
bertopic_easy/main.py
bertopic_easy/models.py
bertopic_easy/naming.py
bertopic_easy-0.3.0.dist-info/METADATA
bertopic_easy-0.3.0.dist-info/WHEEL
bertopic_easy-0.3.0.dist-info/RECORD
