Metadata-Version: 2.3
Name: bertopic-easy
Version: 0.3.0
Summary: 
Author: Boris Dev
Author-email: boris.dev@gmail.com
Requires-Python: >=3.11,<3.13
Classifier: Programming Language :: Python :: 3
Classifier: Programming Language :: Python :: 3.11
Classifier: Programming Language :: Python :: 3.12
Requires-Dist: bertopic (>=0.16.4,<0.17.0)
Requires-Dist: diskcache (>=5.6.3,<6.0.0)
Requires-Dist: instructor (>=1.7.0,<2.0.0)
Requires-Dist: loguru (>=0.7.2,<0.8.0)
Requires-Dist: more-itertools (>=10.6.0,<11.0.0)
Requires-Dist: numpy (==1.26.4)
Requires-Dist: openai (>=1.58.1,<2.0.0)
Requires-Dist: pydantic (>=2.7.1,<3.0.0)
Requires-Dist: pytest-asyncio (>=0.25.3,<0.26.0)
Requires-Dist: python-dotenv (>=1.0.1,<2.0.0)
Requires-Dist: update (>=0.0.1,<0.0.2)
